exceptors/__init__.py
exceptors/core/__init__.py
exceptors/tests/__init__.py
exceptors/tests/test_0.py
exceptors-0.2.1.dist-info/licenses/LICENSE.txt
exceptors-0.2.1.dist-info/METADATA
exceptors-0.2.1.dist-info/WHEEL
exceptors-0.2.1.dist-info/top_level.txt
exceptors-0.2.1.dist-info/RECORD
