Metadata-Version: 2.4
Name: exceptors
Version: 0.2.1
Summary: This project allows to capture exceptions easily.
Author-email: Johannes <johannes.programming@gmail.com>
License: The MIT License (MIT)
Project-URL: Download, https://pypi.org/project/exceptors/#files
Project-URL: Index, https://pypi.org/project/exceptors/
Project-URL: Source, https://github.com/johannes-programming/exceptors/
Project-URL: Website, https://exceptors.johannes-programming.online/
Classifier: Development Status :: 3 - Alpha
Classifier: License :: OSI Approved :: MIT License
Classifier: Natural Language :: English
Classifier: Operating System :: OS Independent
Classifier: Programming Language :: Python
Classifier: Programming Language :: Python :: 3
Classifier: Programming Language :: Python :: 3 :: Only
Classifier: Typing :: Typed
Requires-Python: >=3.11
License-File: LICENSE.txt
Requires-Dist: catchlib>=1.0
Dynamic: license-file
